geometricLib/__init__.py
geometricLib/geometric.py
geometricLib-0.0.3.dist-info/METADATA
geometricLib-0.0.3.dist-info/WHEEL
geometricLib-0.0.3.dist-info/top_level.txt
geometricLib-0.0.3.dist-info/RECORD
