Metadata-Version: 2.1
Name: geometricLib
Version: 0.0.3
Summary: calculates the area of a circle by radius and a triangle by three sides
Home-page: https://github.com/uhiintezz/geometricLib
Author: blank1xs
Author-email: oignatevich@gmail.com
License: UNKNOWN
Project-URL: GitHub, https://github.com/uhiintezz
Platform: UNKNOWN
Requires-Python: >=3.6
